{"__type__":"cc.JsonAsset","_name":"GuideConfig","json":{"1":{"1":{"guideId":1,"type":0,"direction":1,"tips":"点击选择武器","start":{"value":100003,"type":2},"target":"getEquipGrid(EquipPos.WEAPON)","view":"RoleWin","stepId":1},"2":{"guideId":1,"type":0,"direction":0,"target":"list.getElementAt(0).changeBtn","tips":"点击穿戴武器","view":"RoleChooseEquipWin","stepId":2},"3":{"guideId":1,"type":0,"direction":0,"tips":"返回战斗场景","overs":[{"value":100004,"type":1}],"target":"closeBtn","view":"UIView2","stepId":3}},"2":{"1":{"guideId":2,"type":0,"overs":[{"value":100010,"type":1}],"stepId":1,"direction":1,"start":{"value":100009,"type":2},"tips":"点击熔炼装备","target":"equip.getGuildButton()","view":"SmeltEquipTotalWin"}},"3":{"1":{"guideId":3,"type":0,"direction":1,"tips":"点击强化装备","start":{"value":100010,"type":2},"target":"boostPanel.getGuildButton()","view":"ForgeWin","stepId":1},"2":{"guideId":3,"type":0,"direction":0,"tips":"返回战斗场景","overs":[{"value":100011,"type":1}],"target":"closeBtn","view":"UIView2","stepId":2}},"4":{"1":{"guideId":4,"type":0,"direction":1,"tips":"查看神器碎片","start":{"value":100013,"type":2},"target":"artifactWin.guide0","view":"LiLianWin","stepId":1},"2":{"guideId":4,"type":0,"direction":1,"target":"btnOpen","tips":"激活神器碎片","view":"ArtifactChipOpenWin","stepId":2},"3":{"guideId":4,"type":0,"direction":0,"tips":"返回战斗场景","overs":[{"value":100014,"type":1}],"target":"closeBtn","view":"UIView2","stepId":3}},"5":{"1":{"guideId":5,"type":0,"overs":[{"value":100019,"type":1}],"stepId":1,"direction":1,"start":{"value":100018,"type":2},"tips":"点击熔炼装备","target":"equip.getGuildButton()","view":"SmeltEquipTotalWin"}},"6":{"1":{"guideId":6,"type":0,"overs":[{"value":100020,"type":1}],"stepId":1,"direction":1,"start":{"value":100019,"type":2},"tips":"点击强化装备","target":"boostPanel.getGuildButton()","view":"ForgeWin"}},"7":{"1":{"guideId":7,"type":0,"direction":0,"tips":"查看神器碎片","start":{"value":100026,"type":2},"target":"artifactWin.guide1","view":"LiLianWin","stepId":1},"2":{"guideId":7,"type":0,"direction":0,"target":"btnOpen","tips":"激活神器碎片","view":"ArtifactChipOpenWin","stepId":2},"3":{"guideId":7,"type":0,"direction":0,"target":"artifactWin.btnOpen","tips":"激活火龙之心","view":"LiLianWin","stepId":3},"4":{"guideId":7,"type":0,"direction":0,"target":"closeBtn","tips":"点击关闭神器","view":"UIView2","stepId":4},"5":{"guideId":7,"type":0,"direction":0,"tips":"返回战斗场景","overs":[{"value":100027,"type":1}],"target":"closeBtn","view":"UIView2","stepId":5}},"8":{"1":{"guideId":8,"type":1,"direction":0,"tips":"攻击归属者","start":{"value":100050,"type":2},"target":"attackPlayer","view":"WorldBossUiInfo","stepId":1}},"9":{"1":{"guideId":9,"type":1,"direction":0,"tips":"攻击敌人","start":{"type":4},"target":"list2.getChildAt(0).roleHead","view":"WorldBossUiInfo","stepId":1}}}}