{"__type__":"cc.JsonAsset","_name":"ActivityType18Config","json":{"302":{"0":{"Id":302,"showType":1,"index":0,"showDrop":[{"id":204077,"type":1,"count":1},{"id":204079,"type":1,"count":1},{"id":204078,"type":1,"count":1},{"id":204080,"type":1,"count":1},{"id":204081,"type":1,"count":1},{"id":204082,"type":1,"count":1},{"id":204083,"type":1,"count":1},{"id":204084,"type":1,"count":1},{"id":101421,"type":1,"count":1},{"id":102421,"type":1,"count":1},{"id":111421,"type":1,"count":1},{"id":131421,"type":1,"count":1},{"id":141421,"type":1,"count":1},{"id":161421,"type":1,"count":1},{"id":151421,"type":1,"count":1},{"id":171421,"type":1,"count":1}]},"1":{"Id":302,"yb":500,"index":1,"count":1},"2":{"Id":302,"yb":5000,"index":2,"count":10}},"502":{"0":{"Id":502,"showType":1,"index":0,"showDrop":[{"id":204077,"type":1,"count":1},{"id":204079,"type":1,"count":1},{"id":204078,"type":1,"count":1},{"id":204080,"type":1,"count":1},{"id":204081,"type":1,"count":1},{"id":204082,"type":1,"count":1},{"id":204083,"type":1,"count":1},{"id":204084,"type":1,"count":1},{"id":910051,"type":1,"count":1},{"id":910052,"type":1,"count":1},{"id":910053,"type":1,"count":1},{"id":910054,"type":1,"count":1},{"id":910055,"type":1,"count":1},{"id":910056,"type":1,"count":1},{"id":910057,"type":1,"count":1},{"id":910058,"type":1,"count":1}]},"1":{"itemCount":1,"index":1,"Id":502,"count":1,"yb":500,"item":200982},"2":{"itemCount":10,"index":2,"Id":502,"count":10,"yb":5000,"item":200982}},"510":{"0":{"Id":510,"showType":1,"index":0,"showDrop":[{"id":204077,"type":1,"count":1},{"id":204079,"type":1,"count":1},{"id":204078,"type":1,"count":1},{"id":204080,"type":1,"count":1},{"id":204081,"type":1,"count":1},{"id":204082,"type":1,"count":1},{"id":204083,"type":1,"count":1},{"id":204084,"type":1,"count":1},{"id":910051,"type":1,"count":1},{"id":910052,"type":1,"count":1},{"id":910053,"type":1,"count":1},{"id":910054,"type":1,"count":1},{"id":910055,"type":1,"count":1},{"id":910056,"type":1,"count":1},{"id":910057,"type":1,"count":1},{"id":910058,"type":1,"count":1}]},"1":{"itemCount":1,"index":1,"Id":510,"count":1,"yb":500,"item":200982},"2":{"itemCount":10,"index":2,"Id":510,"count":10,"yb":5000,"item":200982}},"562":{"0":{"Id":562,"showType":1,"index":0,"showDrop":[{"id":205006,"type":1,"count":1},{"id":200302,"type":1,"count":1},{"id":200143,"type":1,"count":1},{"id":200145,"type":1,"count":1},{"id":200146,"type":1,"count":1},{"id":200148,"type":1,"count":1},{"id":200147,"type":1,"count":1},{"id":200149,"type":1,"count":1},{"id":101421,"type":1,"count":1},{"id":102421,"type":1,"count":1},{"id":111421,"type":1,"count":1},{"id":410001,"type":1,"count":1},{"id":410002,"type":1,"count":1},{"id":410003,"type":1,"count":1},{"id":410004,"type":1,"count":1},{"id":171421,"type":1,"count":1}]},"1":{"itemCount":1,"index":1,"Id":562,"count":1,"yb":500,"item":200982},"2":{"itemCount":10,"index":2,"Id":562,"count":10,"yb":5000,"item":200982}},"573":{"0":{"Id":573,"showType":1,"index":0,"showDrop":[{"id":205006,"type":1,"count":1},{"id":200302,"type":1,"count":1},{"id":200143,"type":1,"count":1},{"id":200145,"type":1,"count":1},{"id":200146,"type":1,"count":1},{"id":200148,"type":1,"count":1},{"id":200147,"type":1,"count":1},{"id":200149,"type":1,"count":1},{"id":101421,"type":1,"count":1},{"id":102421,"type":1,"count":1},{"id":111421,"type":1,"count":1},{"id":410001,"type":1,"count":1},{"id":410002,"type":1,"count":1},{"id":410003,"type":1,"count":1},{"id":410004,"type":1,"count":1},{"id":171421,"type":1,"count":1}]},"1":{"itemCount":1,"index":1,"Id":573,"count":1,"yb":500,"item":200982},"2":{"itemCount":10,"index":2,"Id":573,"count":10,"yb":5000,"item":200982}},"574":{"0":{"Id":574,"showType":1,"index":0,"showDrop":[{"id":205006,"type":1,"count":1},{"id":200302,"type":1,"count":1},{"id":200143,"type":1,"count":1},{"id":200145,"type":1,"count":1},{"id":200146,"type":1,"count":1},{"id":200148,"type":1,"count":1},{"id":200147,"type":1,"count":1},{"id":200149,"type":1,"count":1},{"id":101421,"type":1,"count":1},{"id":102421,"type":1,"count":1},{"id":111421,"type":1,"count":1},{"id":410001,"type":1,"count":1},{"id":410002,"type":1,"count":1},{"id":410003,"type":1,"count":1},{"id":410004,"type":1,"count":1},{"id":171421,"type":1,"count":1}]},"1":{"itemCount":1,"index":1,"Id":574,"count":1,"yb":500,"item":200982},"2":{"itemCount":10,"index":2,"Id":574,"count":10,"yb":5000,"item":200982}},"802":{"0":{"Id":802,"showType":1,"index":0,"showDrop":[{"id":204077,"type":1,"count":1},{"id":204079,"type":1,"count":1},{"id":204078,"type":1,"count":1},{"id":204080,"type":1,"count":1},{"id":204081,"type":1,"count":1},{"id":204082,"type":1,"count":1},{"id":204083,"type":1,"count":1},{"id":204084,"type":1,"count":1},{"id":910051,"type":1,"count":1},{"id":910052,"type":1,"count":1},{"id":910053,"type":1,"count":1},{"id":910054,"type":1,"count":1},{"id":910055,"type":1,"count":1},{"id":910056,"type":1,"count":1},{"id":910057,"type":1,"count":1},{"id":910058,"type":1,"count":1}]},"1":{"itemCount":1,"index":1,"Id":802,"count":1,"yb":500,"item":200982},"2":{"itemCount":10,"index":2,"Id":802,"count":10,"yb":5000,"item":200982}},"810":{"0":{"Id":810,"showType":1,"index":0,"showDrop":[{"id":204077,"type":1,"count":1},{"id":204079,"type":1,"count":1},{"id":204078,"type":1,"count":1},{"id":204080,"type":1,"count":1},{"id":204081,"type":1,"count":1},{"id":204082,"type":1,"count":1},{"id":204083,"type":1,"count":1},{"id":204084,"type":1,"count":1},{"id":910051,"type":1,"count":1},{"id":910052,"type":1,"count":1},{"id":910053,"type":1,"count":1},{"id":910054,"type":1,"count":1},{"id":910055,"type":1,"count":1},{"id":910056,"type":1,"count":1},{"id":910057,"type":1,"count":1},{"id":910058,"type":1,"count":1}]},"1":{"itemCount":1,"index":1,"Id":810,"count":1,"yb":500,"item":200982},"2":{"itemCount":10,"index":2,"Id":810,"count":10,"yb":5000,"item":200982}},"821":{"0":{"Id":821,"showType":1,"index":0,"showDrop":[{"id":204077,"type":1,"count":1},{"id":204079,"type":1,"count":1},{"id":204078,"type":1,"count":1},{"id":204080,"type":1,"count":1},{"id":204081,"type":1,"count":1},{"id":204082,"type":1,"count":1},{"id":204083,"type":1,"count":1},{"id":204084,"type":1,"count":1},{"id":910051,"type":1,"count":1},{"id":910052,"type":1,"count":1},{"id":910053,"type":1,"count":1},{"id":910054,"type":1,"count":1},{"id":910055,"type":1,"count":1},{"id":910056,"type":1,"count":1},{"id":910057,"type":1,"count":1},{"id":910058,"type":1,"count":1}]},"1":{"itemCount":1,"index":1,"Id":821,"count":1,"yb":500,"item":200982},"2":{"itemCount":10,"index":2,"Id":821,"count":10,"yb":5000,"item":200982}}}}