{"__type__":"cc.JsonAsset","_name":"ShenShouBase","json":{"1":{"activeImg":"icon_s1","minLevel":[0,0,0,0,0],"id":1,"iconImg":"icon_s1b","skill":[1]},"2":{"activeImg":"icon_s2","minLevel":[2,2,0,0,0],"id":2,"iconImg":"icon_s2b","skill":[6]},"3":{"activeImg":"icon_s3","minLevel":[2,2,2,2,2],"id":3,"iconImg":"icon_s3b","skill":[2]},"4":{"activeImg":"icon_s4","minLevel":[5,5,2,2,2],"id":4,"iconImg":"icon_s4b","skill":[7]},"5":{"activeImg":"icon_s5","minLevel":[5,5,5,5,2],"id":5,"iconImg":"icon_s5b","skill":[3]},"6":{"activeImg":"icon_s6","minLevel":[5,5,5,5,5],"id":6,"iconImg":"icon_s6b","skill":[8]},"7":{"activeImg":"icon_s7","minLevel":[8,5,5,5,5],"id":7,"iconImg":"icon_s7b","skill":[11,3]},"8":{"activeImg":"icon_s8","minLevel":[8,8,8,5,5],"id":8,"iconImg":"icon_s8b","skill":[16,8]},"9":{"activeImg":"icon_s9","minLevel":[8,8,8,8,8],"id":9,"iconImg":"icon_s9b","skill":[12,3]}}}