{"__type__":"cc.JsonAsset","_name":"ActivityType8Config","json":{"201":{"1":{"index":1,"rewardsNum":150,"Id":201,"rewards":1665201,"ybCount":888,"showType":1},"2":{"rewardsNum":400,"index":2,"showType":1,"Id":201,"cond":1,"ybCount":2888,"rewards":1665202},"3":{"rewardsNum":800,"index":3,"showType":1,"Id":201,"cond":2,"ybCount":5888,"rewards":1665203},"4":{"rewardsNum":1200,"index":4,"showType":1,"Id":201,"cond":3,"ybCount":8888,"rewards":1665204},"5":{"rewardsNum":1600,"index":5,"showType":1,"Id":201,"cond":4,"ybCount":12888,"rewards":1665205},"6":{"rewardsNum":2100,"index":6,"showType":1,"Id":201,"cond":5,"ybCount":16888,"rewards":1665206},"7":{"rewardsNum":2100,"index":7,"showType":1,"Id":201,"cond":6,"ybCount":16888,"rewards":1665207},"8":{"rewardsNum":2100,"index":8,"showType":1,"Id":201,"cond":7,"ybCount":16888,"rewards":1665208},"9":{"rewardsNum":2100,"index":9,"showType":1,"Id":201,"cond":8,"ybCount":16888,"rewards":1665209},"10":{"rewardsNum":2100,"index":10,"showType":1,"Id":201,"cond":9,"ybCount":16888,"rewards":1665209},"11":{"rewardsNum":2100,"index":11,"showType":1,"Id":201,"cond":10,"ybCount":16888,"rewards":1665209},"12":{"rewardsNum":2100,"index":12,"showType":1,"Id":201,"cond":11,"ybCount":16888,"rewards":1665209}}}}